manifoldpy/__init__.py
manifoldpy/api.py
manifoldpy/cache_utils.py
manifoldpy/calibration.py
manifoldpy/config.py
manifoldpy-1.1.2.dist-info/LICENSE
manifoldpy-1.1.2.dist-info/METADATA
manifoldpy-1.1.2.dist-info/WHEEL
manifoldpy-1.1.2.dist-info/top_level.txt
manifoldpy-1.1.2.dist-info/RECORD
