Metadata-Version: 2.1
Name: manifoldpy
Version: 1.1.2
Summary: Python tools for working with Manifold Markets
Author-email: Vincent Luczkow <vincent.luczkow@gmail.com>
License: MIT License
Project-URL: Homepage, https://github.com/vluzko/manifoldpy
Project-URL: Bug Tracker, https://github.com/vluzko/manifoldpy/issues
Classifier: Programming Language :: Python :: 3
Classifier: License :: OSI Approved :: MIT License
Classifier: Operating System :: OS Independent
Requires-Python: >=3.7
License-File: LICENSE
Requires-Dist: attrs (==22.1.0)
Requires-Dist: matplotlib (==3.5.2)
Requires-Dist: numpy (==1.23.1)
Requires-Dist: pandas (==1.5.1)
Requires-Dist: requests (==2.28.1)
Requires-Dist: scipy (==1.9.3)
Provides-Extra: dev
Requires-Dist: coverage (==6.5.0) ; extra == 'dev'
Requires-Dist: mypy (==0.991) ; extra == 'dev'
Requires-Dist: pytest (==7.1.2) ; extra == 'dev'
Requires-Dist: pandas-stubs (>=1.5.2) ; extra == 'dev'
Requires-Dist: Sphinx (==5.3.0) ; extra == 'dev'
Requires-Dist: sphinx-rtd-theme (==1.1.1) ; extra == 'dev'
Requires-Dist: types-pytz (==2022.6.0.1) ; extra == 'dev'
Requires-Dist: types-requests (==2.28.11.4) ; extra == 'dev'
Requires-Dist: types-urllib3 (==1.26.25.3) ; extra == 'dev'
